tno/zkp/modulus_linear_form/__init__.py
tno/zkp/modulus_linear_form/modulus_linear_form.py
tno/zkp/modulus_linear_form/py.typed
tno/zkp/modulus_linear_form/test/__init__.py
tno/zkp/modulus_linear_form/test/conftest.py
tno/zkp/modulus_linear_form/test/test_linear_form_input.py
tno/zkp/modulus_linear_form/test/test_linear_form_output.py
tno/zkp/modulus_linear_form/test/test_modulus_linear_form.py
tno/zkp/templates/__init__.py
tno/zkp/templates/compression_mechanism.py
tno/zkp/templates/homomorphism.py
tno/zkp/templates/py.typed
tno/zkp/templates/sigma_protocol.py
tno/zkp/templates/test/__init__.py
tno/zkp/templates/test/conftest.py
tno/zkp/templates/test/test_basicsigmaprotocol.py
tno/zkp/templates/test/test_compressedsigmaprotocol.py
tno.zkp.templates-0.1.1.post1.dist-info/LICENSE
tno.zkp.templates-0.1.1.post1.dist-info/METADATA
tno.zkp.templates-0.1.1.post1.dist-info/WHEEL
tno.zkp.templates-0.1.1.post1.dist-info/top_level.txt
tno.zkp.templates-0.1.1.post1.dist-info/RECORD
