Metadata-Version: 2.1
Name: tno.zkp.templates
Version: 0.1.1.post1
Summary: ZKP templates module
Author-email: TNO PET Lab <petlab@tno.nl>
Maintainer-email: TNO PET Lab <petlab@tno.nl>
License: Apache License, Version 2.0
Project-URL: Homepage, https://pet.tno.nl/
Project-URL: Documentation, https://docs.pet.tno.nl/zkp/templates/0.1.1
Project-URL: Source, https://github.com/TNO-ZKP/templates
Keywords: TNO,ZKP,zero-knowledge proof
Platform: any
Classifier: License :: OSI Approved :: Apache Software License
Classifier: Programming Language :: Python :: 3
Classifier: Operating System :: OS Independent
Classifier: Intended Audience :: Developers
Classifier: Intended Audience :: Information Technology
Classifier: Intended Audience :: Science/Research
Classifier: Typing :: Typed
Classifier: Topic :: Security :: Cryptography
Requires-Python: >=3.8
License-File: LICENSE
Requires-Dist: typing-extensions ~=4.0 ; python_version < "3.11"
Provides-Extra: tests
Requires-Dist: pytest ; extra == 'tests'
Requires-Dist: sympy ; extra == 'tests'
